torchfbm/__init__.py
torchfbm/analysis.py
torchfbm/augmentations.py
torchfbm/dfa.py
torchfbm/estimators.py
torchfbm/generators.py
torchfbm/layers.py
torchfbm/loss.py
torchfbm/online.py
torchfbm/processes.py
torchfbm/rl.py
torchfbm/schedulers.py
torchfbm/sde.py
torchfbm/transforms.py
torchfbm/utils.py
torchfbm/tests/conftest.py
torchfbm/tests/test_analysis.py
torchfbm/tests/test_augmentations.py
torchfbm/tests/test_dfa.py
torchfbm/tests/test_estimators.py
torchfbm/tests/test_generators.py
torchfbm/tests/test_layers.py
torchfbm/tests/test_loss.py
torchfbm/tests/test_online.py
torchfbm/tests/test_processes.py
torchfbm/tests/test_rl.py
torchfbm/tests/test_schedulers.py
torchfbm/tests/test_sde.py
torchfbm/tests/test_transforms.py
torchfbm-0.3.0.dist-info/licenses/LICENSE
torchfbm-0.3.0.dist-info/METADATA
torchfbm-0.3.0.dist-info/WHEEL
torchfbm-0.3.0.dist-info/top_level.txt
torchfbm-0.3.0.dist-info/RECORD
