Metadata-Version: 2.4
Name: torchfbm
Version: 0.3.0
Summary: High-performance Fractional Brownian Motion toolkit for PyTorch
Home-page: https://github.com/i-habib/torchfbm
Author: Ivan Habib
Author-email: Ivan Habib <ivan.habib4@gmail.com>
License: MIT
Project-URL: Homepage, https://github.com/Coder9872/torchfbm
Project-URL: Documentation, https://coder9872.github.io/torchfbm/
Project-URL: Repository, https://github.com/Coder9872/torchfbm
Project-URL: Issues, https://github.com/Coder9872/torchfbm/issues
Keywords: fractional brownian motion,pytorch,stochastic processes,hurst exponent,deep learning
Classifier: Development Status :: 4 - Beta
Classifier: Intended Audience :: Developers
Classifier: Intended Audience :: Science/Research
Classifier: Topic :: Scientific/Engineering :: Artificial Intelligence
Classifier: Topic :: Scientific/Engineering :: Mathematics
Classifier: Programming Language :: Python :: 3
Classifier: Programming Language :: Python :: 3.8
Classifier: Programming Language :: Python :: 3.9
Classifier: Programming Language :: Python :: 3.10
Classifier: Programming Language :: Python :: 3.11
Classifier: Programming Language :: Python :: 3.12
Classifier: License :: OSI Approved :: MIT License
Classifier: Operating System :: OS Independent
Requires-Python: >=3.7
License-File: LICENSE
Requires-Dist: torch>=1.9.0
Requires-Dist: numpy>=1.19.0
Provides-Extra: dev
Requires-Dist: pytest>=6.0; extra == "dev"
Requires-Dist: pytest-cov>=2.12.0; extra == "dev"
Provides-Extra: rl
Requires-Dist: stable-baselines3>=1.0; extra == "rl"
Requires-Dist: gymnasium>=0.26.0; extra == "rl"
Provides-Extra: docs
Requires-Dist: mkdocs-material; extra == "docs"
Requires-Dist: mkdocstrings[python]; extra == "docs"
Dynamic: author
Dynamic: home-page
Dynamic: license-file
Dynamic: requires-python
